Workbook

Sheet Items PRUEBA VTAS
D2: DESTINO | E2: NACIONAL
D3: LISTA DE PRECIOS | E3: 002
D4: DESCUENTO % | E4: 0.15
D5: FLETE APROXIMADO | E5: A definir
B6: Producto / Presentacion | C6: TOP VENTAS | D6: Laboratorio | E6: E-COMME. | F6: Precio distribuidor | G6: Ganancia bodega | H6: Ingreso x mesBodega | I6: Costo envio | J6: Margen40% | K6: Precio final | L6: Rotacion x mes | M6: Ingresos x mes Productopolis | N6: Precio Mercado | O6: Con envio | P6: Dif. Vs Productopolis
A7: 20 | B7: FERTILIDAD MASCULINA FOB AUTOTEST NEWFOUNDLAND CASETE UNIDAD | C7: si | D7: NEWFOUNDLAND | E7: 86000 | F7: 59800 | G7: 26200 | H7: 131000 | I7: 12000 | J7: 120400 | K7: 132400 | L7: 5 | M7: 602000 | N7: 86000 | O7: 95000 | P7: -37400
A8: 27 | B8: MENOPAUSIA FSH AUTOTEST NEWFOUNDLAND MIDSTREAM UNIDAD | C8: si | D8: NEWFOUNDLAND | E8: 69000 | F8: 47900 | G8: 21100 | H8: 105500 | I8: 12000 | J8: 96600 | K8: 108600 | L8: 5 | M8: 483000 | N8: 69000 | O8: 78000 | P8: -30600
A9: 29 | B9: OVULACION LH AUTOTEST NEWFOUNDLAND MIDSTREAM UNIDAD | C9: si | D9: NEWFOUNDLAND | E9: 67000 | F9: 46500 | G9: 20500 | H9: 102500 | I9: 12000 | J9: 93800 | K9: 105800 | L9: 5 | M9: 469000 | N9: 67000 | O9: 76000 | P9: -29800
A10: 39 | B10: SALUD RENAL MAU AUTOTEST NEWFOUNDLAND MIDSTREAM UNIDAD | C10: si | D10: NEWFOUNDLAND | E10: 62000 | F10: 43200 | G10: 18800 | H10: 94000 | I10: 12000 | J10: 86800 | K10: 98800 | L10: 5 | M10: 434000 | N10: 62000 | O10: 71000 | P10: -27800
A11: 41 | B11: SUPER MEGA GAINER VAINILLA IMPORTADO GMN POLVO X 2 LB | C11: si | D11: GMN | E11: 60000 | F11: 41900 | G11: 18100 | H11: 90500 | I11: 12000 | J11: 84000 | K11: 96000 | L11: 5 | M11: 420000 | N11: 70780 | O11: 79780 | P11: -16220
A12: 42 | B12: DEFICIENCIA HIERRO FERRITINA AUTOTEST NEWFOUNDLAND CASETE UNIDAD | C12: si | D12: NEWFOUNDLAND | E12: 59000 | F12: 41200 | G12: 17800 | H12: 89000 | I12: 12000 | J12: 82600 | K12: 94600 | L12: 5 | M12: 413000 | N12: 59000 | O12: 68000 | P12: -26600
A13: 43 | B13: DEFICIENCIA VITAMINA D AUTOTEST NEWFOUNDLAND CASETE UNIDAD | C13: si | D13: NEWFOUNDLAND | E13: 59000 | F13: 41200 | G13: 17800 | H13: 89000 | I13: 12000 | J13: 82600 | K13: 94600 | L13: 5 | M13: 413000 | N13: 59000 | O13: 68000 | P13: -26600
A14: 64 | B14: FIBERLAB (FIBRA DIETARIA) NARANJA PHARBIOLAB® POLVO X 1000 G | C14: si | D14: PHARBIOLAB® | E14: 43000 | F14: 30000 | G14: 13000 | H14: 65000 | I14: 12000 | J14: 60200 | K14: 72200 | L14: 5 | M14: 301000 | N14: 60900 | O14: 69900 | P14: -2300
A15: 65 | B15: GELILAB ADVANCE (COLAGENO HIDROL.) UVA PHARBIOLAB® POLVO X 1000 G | C15: si | D15: PHARBIOLAB® | E15: 43000 | F15: 30000 | G15: 13000 | H15: 65000 | I15: 12000 | J15: 60200 | K15: 72200 | L15: 5 | M15: 301000 | N15: 60900 | O15: 69900 | P15: -2300
A16: 68 | B16: SURELAB ULTRA (MULTIVITAMINICO) VAINILLA PHARBIOLAB® POLVO X 1000 G | C16: si | D16: PHARBIOLAB® | E16: 43000 | F16: 30000 | G16: 13000 | H16: 65000 | I16: 12000 | J16: 60200 | K16: 72200 | L16: 5 | M16: 301000 | N16: 60900 | O16: 69900 | P16: -2300
A17: 94 | B17: CITRATO DE MAGNESIO 900 MG + VIT. C 600 MG GENESIS X 90 CAPSULAS | C17: si | D17: GENESIS | E17: 37000 | F17: 25800 | G17: 11200 | H17: 56000 | I17: 12000 | J17: 51800 | K17: 63800 | L17: 5 | M17: 259000 | N17: 57900 | O17: 66900 | P17: 3100
A18: 95 | B18: CITRATO DE POTASIO 750 MG + CITRATO DE MAGNESIO 750 MG GENESIS X 90 CAPSULAS | C18: si | D18: GENESIS | E18: 37000 | F18: 25800 | G18: 11200 | H18: 56000 | I18: 12000 | J18: 51800 | K18: 63800 | L18: 5 | M18: 259000 | N18: 83850 | O18: 92850 | P18: 29050
... A29: 124 | B29: POWERS'X NATURALPOWER SOBRE X 4 TABLETAS | C29: si | D29: NATURAL POWER | E29: 3000 | F29: 1900 | G29: 1100 | H29: 5500 | I29: 12000 | J29: 4200 | K29: 16200 | L29: 5 | M29: 21000 | N29: 24000 | O29: 33000 | P29: 16800
A30: 128 | B30: VIH AUTOTEST NEWFOUNDLAND MIDSTREAM UNIDAD | C30: si | D30: NEWFOUNDLAND | E30: 0 | F30: 0 | G30: 0 | H30: 0 | I30: 12000 | J30: 0 | K30: 12000 | L30: 5 | M30: 0
D32: INGRESOS BRUTOS | H32: =SUM(H7:H31) -> 1295000 | M32: =SUM(M7:M31) -> 5929000

Sheet Analisis Margen
D2: DESTINO | E2: NACIONAL
D3: LISTA DE PRECIOS | E3: 002
D4: DESCUENTO % | E4: 0.15
D5: FLETE APROXIMADO | E5: A definir
B6: Producto / Presentacion | C6: TOP VENTAS | D6: Laboratorio | E6: E-COMME. | F6: Precio distribuidor | G6: Ganancia bodega | H6: Ingreso x mesBodega | I6: Costo envio | J6: Margen40% | K6: Precio final | L6: Rotacion x mes | M6: Ingresos x mes | N6: Precio Mercado | O6: Con envio | P6: Dif. Vs Productopolis
A7: =+A6+1 -> 1 | B7: POWERS'X NATURALPOWER BOLSA X 100 SOBRES X 400 TABLETAS | D7: NATURAL POWER | E7: 243000 | F7: =+VLOOKUP(B7,Distribuidor!$B$7:$D$533,3,0) -> 170000 | G7: =+E7-F7 -> 73000 | I7: 12000 | J7: =+E7*1.4 -> 340200 | K7: =+J7+I7 -> 352200
A8: =+A7+1 -> 2 | B8: GENGI FRESH PASTILLAS MANA BOMBONERA X 60 SOBRES | D8: EL MANA | E8: 229000 | F8: =+VLOOKUP(B8,Distribuidor!$B$7:$D$533,3,0) -> 160000 | G8: =+E8-F8 -> 69000 | I8: 12000 | J8: =+E8*1.4 -> 320600 | K8: =+J8+I8 -> 332600
A9: =+A8+1 -> 3 | B9: THOR MEGA MASS GAINER VAINILLA MASS PROTEINS POLVO X 13 LB | D9: NATURAL LIFE | E9: 194000 | F9: =+VLOOKUP(B9,Distribuidor!$B$7:$D$533,3,0) -> 135400 | G9: =+E9-F9 -> 58600 | I9: 12000 | J9: =+E9*1.4 -> 271600 | K9: =+J9+I9 -> 283600
A10: =+A9+1 -> 4 | B10: MEGAS'X AZUL NATURALPOWER BOLSA X 100 PASTILLEROS X 300 TABLETAS | D10: NATURAL POWER | E10: 186000 | F10: =+VLOOKUP(B10,Distribuidor!$B$7:$D$533,3,0) -> 130000 | G10: =+E10-F10 -> 56000 | I10: 12000 | J10: =+E10*1.4 -> 260400 | K10: =+J10+I10 -> 272400
A11: =+A10+1 -> 5 | B11: THERA WHEY (PROTEINA LIMPIA) VAINILLA NATURAL LIGHT POLVO X 2 LB | D11: NATURAL LIGHT | E11: 152000 | F11: =+VLOOKUP(B11,Distribuidor!$B$7:$D$533,3,0) -> 106400 | G11: =+E11-F11 -> 45600 | I11: 12000 | J11: =+E11*1.4 -> 212800 | K11: =+J11+I11 -> 224800
A12: =+A11+1 -> 6 | B12: BRONQUISAN PASTILLAS MANA BOMBONERA X 60 SOBRES | D12: EL MANA | E12: 143000 | F12: =+VLOOKUP(B12,Distribuidor!$B$7:$D$533,3,0) -> 100000 | G12: =+E12-F12 -> 43000 | I12: 12000 | J12: =+E12*1.4 -> 200200 | K12: =+J12+I12 -> 212200
A13: =+A12+1 -> 7 | B13: MEGA GAINER VAINILLA IMPORTADO GMN POLVO X 5 LB | D13: GMN | E13: 132000 | F13: =+VLOOKUP(B13,Distribuidor!$B$7:$D$533,3,0) -> 92200 | G13: =+E13-F13 -> 39800 | I13: 12000 | J13: =+E13*1.4 -> 184800 | K13: =+J13+I13 -> 196800
A14: =+A13+1 -> 8 | B14: SUPER MEGA GAINER VAINILLA IMPORTADO GMN POLVO X 5 LB | D14: GMN | E14: 132000 | F14: =+VLOOKUP(B14,Distribuidor!$B$7:$D$533,3,0) -> 92200 | G14: =+E14-F14 -> 39800 | I14: 12000 | J14: =+E14*1.4 -> 184800 | K14: =+J14+I14 -> 196800
A15: =+A14+1 -> 9 | B15: RAPTOR CARNICA FRUTOS ROJOS MASS PROTEINS POLVO X 3 LB | D15: NATURAL LIFE | E15: 126000 | F15: =+VLOOKUP(B15,Distribuidor!$B$7:$D$533,3,0) -> 88000 | G15: =+E15-F15 -> 38000 | I15: 12000 | J15: =+E15*1.4 -> 176400 | K15: =+J15+I15 -> 188400
A16: =+A15+1 -> 10 | B16: SUPREME CREATINA CEREZA IMPORTADO GMN POLVO X 450 G | D16: GMN | E16: 114000 | F16: =+VLOOKUP(B16,Distribuidor!$B$7:$D$533,3,0) -> 79500 | G16: =+E16-F16 -> 34500 | I16: 12000 | J16: =+E16*1.4 -> 159600 | K16: =+J16+I16 -> 171600
A17: =+A16+1 -> 11 | B17: SUPREME CREATINA CITRUS PUNCH IMPORTADO GMN POLVO X 450 G | D17: GMN | E17: 114000 | F17: =+VLOOKUP(B17,Distribuidor!$B$7:$D$533,3,0) -> 79500 | G17: =+E17-F17 -> 34500 | I17: 12000 | J17: =+E17*1.4 -> 159600 | K17: =+J17+I17 -> 171600
A18: =+A17+1 -> 12 | B18: SUPREME CREATINA MANGO BICHE IMPORTADO GMN POLVO X 450 G | D18: GMN | E18: 114000 | F18: =+VLOOKUP(B18,Distribuidor!$B$7:$D$533,3,0) -> 79500 | G18: =+E18-F18 -> 34500 | I18: 12000 | J18: =+E18*1.4 -> 159600 | K18: =+J18+I18 -> 171600
A19: =+A18+1 -> 13 | B19: DETECCION DENGUE NSL AUTOTEST NEWFOUNDLAND CASETE UNIDAD | C19: si | D19: NEWFOUNDLAND | E19: 98000 | F19: =+VLOOKUP(B19,Distribuidor!$B$7:$D$533,3,0) -> 68100 | G19: =+E19-F19 -> 29900 | H19: =+G19*L19 -> 149500 | I19: 12000 | J19: =+E19*1.4 -> 137200 | K19: =+J19+I19 -> 149200 | L19: 5 | M19: =+J19*L19 -> 686000 | N19: =+E19 -> 98000 | O19: =9000+N19 -> 107000 | P19: =+O19-K19 -> -42200
A20: =+A19+1 -> 14 | B20: KIT KERATIN (SHAMPOO 400 ML + ACONDIC. 400 ML + LOCION 320 ML) Mª SALOME | D20: MARIA SALOME | E20: 97000 | F20: =+VLOOKUP(B20,Distribuidor!$B$7:$D$533,3,0) -> 67700 | G20: =+E20-F20 -> 29300 | I20: 12000 | J20: =+E20*1.4 -> 135800 | K20: =+J20+I20 -> 147800
A21: =+A20+1 -> 15 | B21: FORCE CREATINE MASS PROTEINS POLVO X 450 G | D21: NATURAL LIFE | E21: 97000 | F21: =+VLOOKUP(B21,Distribuidor!$B$7:$D$533,3,0) -> 67700 | G21: =+E21-F21 -> 29300 | I21: 12000 | J21: =+E21*1.4 -> 135800 | K21: =+J21+I21 -> 147800
A22: =+A21+1 -> 16 | B22: NITRO MASS VAINILLA IMPORTADO GMN POLVO X 2 LB | D22: GMN | E22: 94000 | F22: =+VLOOKUP(B22,Distribuidor!$B$7:$D$533,3,0) -> 65200 | G22: =+E22-F22 -> 28800 | I22: 12000 | J22: =+E22*1.4 -> 131600 | K22: =+J22+I22 -> 143600
A23: =+A22+1 -> 17 | B23: SALUD PROSTATICA PSA AUTOTEST NEWFOUNDLAND CASETE UNIDAD | C23: si | D23: NEWFOUNDLAND | E23: 93000 | F23: =+VLOOKUP(B23,Distribuidor!$B$7:$D$533,3,0) -> 65100 | G23: =+E23-F23 -> 27900 | H23: =+G23*L23 -> 139500 | I23: 12000 | J23: =+E23*1.4 -> 130200 | K23: =+J23+I23 -> 142200 | L23: 5 | M23: =+J23*L23 -> 651000 | N23: =+E23 -> 93000 | O23: =9000+N23 -> 102000 | P23: =+O23-K23 -> -40200
A24: =+A23+1 -> 18 | B24: BODY RIPPED VAINILLA IMPORTADO GMN POLVO X 2 LB | D24: GMN | E24: 91000 | F24: =+VLOOKUP(B24,Distribuidor!$B$7:$D$533,3,0) -> 63700 | G24: =+E24-F24 -> 27300 | I24: 12000 | J24: =+E24*1.4 -> 127400 | K24: =+J24+I24 -> 139400
A25: =+A24+1 -> 19 | B25: KIT TRADICIONAL (SHAMPOO 400 ML + ACONDIC. 400 ML + LOCION 320 ML) Mª SALOME | D25: MARIA SALOME | E25: 89000 | F25: =+VLOOKUP(B25,Distribuidor!$B$7:$D$533,3,0) -> 62200 | G25: =+E25-F25 -> 26800 | I25: 12000 | J25: =+E25*1.4 -> 124600 | K25: =+J25+I25 -> 136600
A26: =+A25+1 -> 20 | B26: FERTILIDAD MASCULINA FOB AUTOTEST NEWFOUNDLAND CASETE UNIDAD | C26: si | D26: NEWFOUNDLAND | E26: 86000 | F26: =+VLOOKUP(B26,Distribuidor!$B$7:$D$533,3,0) -> 59800 | G26: =+E26-F26 -> 26200 | H26: =+G26*L26 -> 131000 | I26: 12000 | J26: =+E26*1.4 -> 120400 | K26: =+J26+I26 -> 132400 | L26: 5 | M26: =+J26*L26 -> 602000 | N26: =+E26 -> 86000 | O26: =9000+N26 -> 95000 | P26: =+O26-K26 -> -37400
A27: =+A26+1 -> 21 | B27: ATOMIC PREWORKOUT FRUTOS ROJOS MASS PROTEINS POLVO X 450 G | D27: NATURAL LIFE | E27: 78000 | F27: =+VLOOKUP(B27,Distribuidor!$B$7:$D$533,3,0) -> 54200 | G27: =+E27-F27 -> 23800 | I27: 12000 | J27: =+E27*1.4 -> 109200 | K27: =+J27+I27 -> 121200
A28: =+A27+1 -> 22 | B28: THUNDER L-GLUTAMINE FRUTOS AMARILLOS MASS PROTEINS POLVO X 450 G | D28: NATURAL LIFE | E28: 78000 | F28: =+VLOOKUP(B28,Distribuidor!$B$7:$D$533,3,0) -> 54200 | G28: =+E28-F28 -> 23800 | I28: 12000 | J28: =+E28*1.4 -> 109200 | K28: =+J28+I28 -> 121200
A29: =+A28+1 -> 23 | B29: SALUD INTESTINAL FOB AUTOTEST NEWFOUNDLAND CASETE UNIDAD | C29: si | D29: NEWFOUNDLAND | E29: 73000 | F29: =+VLOOKUP(B29,Distribuidor!$B$7:$D$533,3,0) -> 50500 | G29: =+E29-F29 -> 22500 | H29: =+G29*L29 -> 112500 | I29: 12000 | J29: =+E29*1.4 -> 102200 | K29: =+J29+I29 -> 114200 | L29: 5 | M29: =+J29*L29 -> 511000 | N29: =+E29 -> 73000 | O29: =9000+N29 -> 82000 | P29: =+O29-K29 -> -32200
A30: =+A29+1 -> 24 | B30: TIROIDES TSH AUTOTEST NEWFOUNDLAND CASETE UNIDAD | C30: si | D30: NEWFOUNDLAND | E30: 73000 | F30: =+VLOOKUP(B30,Distribuidor!$B$7:$D$533,3,0) -> 50500 | G30: =+E30-F30 -> 22500 | H30: =+G30*L30 -> 112500 | I30: 12000 | J30: =+E30*1.4 -> 102200 | K30: =+J30+I30 -> 114200 | L30: 5 | M30: =+J30*L30 -> 511000 | N30: =+E30 -> 73000 | O30: =9000+N30 -> 82000 | P30: =+O30-K30 -> -32200
A31: =+A30+1 -> 25 | B31: ULCERA ESTOMACAL H. PYLORI AUTOTEST NEWFOUNDLAND CASETE UNIDAD | C31: si | D31: NEWFOUNDLAND | E31: 73000 | F31: =+VLOOKUP(B31,Distribuidor!$B$7:$D$533,3,0) -> 50500 | G31: =+E31-F31 -> 22500 | H31: =+G31*L31 -> 112500 | I31: 12000 | J31: =+E31*1.4 -> 102200 | K31: =+J31+I31 -> 114200 | L31: 5 | M31: =+J31*L31 -> 511000 | N31: =+E31 -> 73000 | O31: =9000+N31 -> 82000 | P31: =+O31-K31 -> -32200
A32: =+A31+1 -> 26 | B32: SUTRA (POTENCIADOR) GENESIS DISPLAY X 30 SACHETS | D32: GENESIS | E32: 72000 | F32: =+VLOOKUP(B32,Distribuidor!$B$7:$D$533,3,0) -> 50000 | G32: =+E32-F32 -> 22000 | I32: 12000 | J32: =+E32*1.4 -> 100800 | K32: =+J32+I32 -> 112800
A33: =+A32+1 -> 27 | B33: MENOPAUSIA FSH AUTOTEST NEWFOUNDLAND MIDSTREAM UNIDAD | C33: si | D33: NEWFOUNDLAND | E33: 69000 | F33: =+VLOOKUP(B33,Distribuidor!$B$7:$D$533,3,0) -> 47900 | G33: =+E33-F33 -> 21100 | H33: =+G33*L33 -> 105500 | I33: 12000 | J33: =+E33*1.4 -> 96600 | K33: =+J33+I33 -> 108600 | L33: 5 | M33: =+J33*L33 -> 483000 | N33: =+E33 -> 69000 | O33: =9000+N33 -> 78000 | P33: =+O33-K33 -> -30600
A34: =+A33+1 -> 28 | B34: THOR MEGA MASS GAINER VAINILLA MASS PROTEINS POLVO X 3,5 LB | D34: NATURAL LIFE | E34: 68000 | F34: =+VLOOKUP(B34,Distribuidor!$B$7:$D$533,3,0) -> 47400 | G34: =+E34-F34 -> 20600 | I34: 12000 | J34: =+E34*1.4 -> 95200 | K34: =+J34+I34 -> 107200
A35: =+A34+1 -> 29 | B35: OVULACION LH AUTOTEST NEWFOUNDLAND MIDSTREAM UNIDAD | C35: si | D35: NEWFOUNDLAND | E35: 67000 | F35: =+VLOOKUP(B35,Distribuidor!$B$7:$D$533,3,0) -> 46500 | G35: =+E35-F35 -> 20500 | H35: =+G35*L35 -> 102500 | I35: 12000 | J35: =+E35*1.4 -> 93800 | K35: =+J35+I35 -> 105800 | L35: 5 | M35: =+J35*L35 -> 469000 | N35: =+E35 -> 67000 | O35: =9000+N35 -> 76000 | P35: =+O35-K35 -> -29800
A36: =+A35+1 -> 30 | B36: COLAGENO MARINO HIDRO. + BIOTINA + VIT. E VAINILLA VITAMIN & LINE POLVO X 1000 G | D36: VITAMIN & LINE | E36: 66000 | F36: =+VLOOKUP(B36,Distribuidor!$B$7:$D$533,3,0) -> 46200 | G36: =+E36-F36 -> 19800 | I36: 12000 | J36: =+E36*1.4 -> 92400 | K36: =+J36+I36 -> 104400
A37: =+A36+1 -> 31 | B37: RESPIRIN GRIPA (ANTI-GRIPAL) SANLY DISPLAY X 10 BLISTER X 100 CAPSULAS | D37: SANLY | E37: 65000 | F37: =+VLOOKUP(B37,Distribuidor!$B$7:$D$533,3,0) -> 45000 | G37: =+E37-F37 -> 20000 | I37: 12000 | J37: =+E37*1.4 -> 91000 | K37: =+J37+I37 -> 103000
A38: =+A37+1 -> 32 | B38: MELATONINA 3 MG IMPORTADO VITAMIN & LINE X 100 SOFTGELS | D38: VITAMIN & LINE | E38: 64000 | F38: =+VLOOKUP(B38,Distribuidor!$B$7:$D$533,3,0) -> 44300 | G38: =+E38-F38 -> 19700 | I38: 12000 | J38: =+E38*1.4 -> 89600 | K38: =+J38+I38 -> 101600
A39: =+A38+1 -> 33 | B39: EXTREME MEGA MASS GAINER VAINILLA MASS PROTEINS POLVO X 3 LB | D39: NATURAL LIFE | E39: 63000 | F39: =+VLOOKUP(B39,Distribuidor!$B$7:$D$533,3,0) -> 44000 | G39: =+E39-F39 -> 19000 | I39: 12000 | J39: =+E39*1.4 -> 88200 | K39: =+J39+I39 -> 100200
A40: =+A39+1 -> 34 | B40: BIOTINA 900 MCG VITAMINE & LINE X 100 SOFTGELS | D40: VITAMIN & LINE | E40: 63000 | F40: =+VLOOKUP(B40,Distribuidor!$B$7:$D$533,3,0) -> 43700 | G40: =+E40-F40 -> 19300 | I40: 12000 | J40: =+E40*1.4 -> 88200 | K40: =+J40+I40 -> 100200
A41: =+A40+1 -> 35 | B41: COLAGENO MARINO CON PEPTIDOS UVA 3Q DISPLAY X 30 SACHETS | D41: VARIOS | E41: 63000 | F41: =+VLOOKUP(B41,Distribuidor!$B$7:$D$533,3,0) -> 43500 | G41: =+E41-F41 -> 19500 | I41: 12000 | J41: =+E41*1.4 -> 88200 | K41: =+J41+I41 -> 100200
A42: =+A41+1 -> 36 | B42: REGUF (ANTIACIDO) MENTA 3Q DISPLAY X 30 SACHETS | D42: VARIOS | E42: 63000 | F42: =+VLOOKUP(B42,Distribuidor!$B$7:$D$533,3,0) -> 43500 | G42: =+E42-F42 -> 19500 | I42: 12000 | J42: =+E42*1.4 -> 88200 | K42: =+J42+I42 -> 100200
A43: =+A42+1 -> 37 | B43: RHEUMADAUL MANA X 60 CAPSULAS | D43: EL MANA | E43: 62000 | F43: =+VLOOKUP(B43,Distribuidor!$B$7:$D$533,3,0) -> 43000 | G43: =+E43-F43 -> 19000 | I43: 12000 | J43: =+E43*1.4 -> 86800 | K43: =+J43+I43 -> 98800
A44: =+A43+1 -> 38 | B44: KIT CONTROL CASPA (SHAMPOO 400 ML + LOCION 320 ML) Mª SALOME | D44: MARIA SALOME | E44: 62000 | F44: =+VLOOKUP(B44,Distribuidor!$B$7:$D$533,3,0) -> 42800 | G44: =+E44-F44 -> 19200 | I44: 12000 | J44: =+E44*1.4 -> 86800 | K44: =+J44+I44 -> 98800
A45: =+A44+1 -> 39 | B45: SALUD RENAL MAU AUTOTEST NEWFOUNDLAND MIDSTREAM UNIDAD | C45: si | D45: NEWFOUNDLAND | E45: 62000 | F45: =+VLOOKUP(B45,Distribuidor!$B$7:$D$533,3,0) -> 43200 | G45: =+E45-F45 -> 18800 | H45: =+G45*L45 -> 94000 | I45: 12000 | J45: =+E45*1.4 -> 86800 | K45: =+J45+I45 -> 98800 | L45: 5 | M45: =+J45*L45 -> 434000 | N45: =+E45 -> 62000 | O45: =9000+N45 -> 71000 | P45: =+O45-K45 -> -27800
A46: =+A45+1 -> 40 | B46: MEGA GAINER VAINILLA IMPORTADO GMN POLVO X 2 LB | D46: GMN | E46: 60000 | F46: =+VLOOKUP(B46,Distribuidor!$B$7:$D$533,3,0) -> 41900 | G46: =+E46-F46 -> 18100 | I46: 12000 | J46: =+E46*1.4 -> 84000 | K46: =+J46+I46 -> 96000
A47: =+A46+1 -> 41 | B47: SUPER MEGA GAINER VAINILLA IMPORTADO GMN POLVO X 2 LB | C47: si | D47: GMN | E47: 60000 | F47: =+VLOOKUP(B47,Distribuidor!$B$7:$D$533,3,0) -> 41900 | G47: =+E47-F47 -> 18100 | H47: =+G47*L47 -> 90500 | I47: 12000 | J47: =+E47*1.4 -> 84000 | K47: =+J47+I47 -> 96000 | L47: 5 | M47: =+J47*L47 -> 420000 | N47: 70780 | O47: =9000+N47 -> 79780 | P47: =+O47-K47 -> -16220
A48: =+A47+1 -> 42 | B48: DEFICIENCIA HIERRO FERRITINA AUTOTEST NEWFOUNDLAND CASETE UNIDAD | C48: si | D48: NEWFOUNDLAND | E48: 59000 | F48: =+VLOOKUP(B48,Distribuidor!$B$7:$D$533,3,0) -> 41200 | G48: =+E48-F48 -> 17800 | H48: =+G48*L48 -> 89000 | I48: 12000 | J48: =+E48*1.4 -> 82600 | K48: =+J48+I48 -> 94600 | L48: 5 | M48: =+J48*L48 -> 413000 | N48: =+E48 -> 59000 | O48: =9000+N48 -> 68000 | P48: =+O48-K48 -> -26600
A49: =+A48+1 -> 43 | B49: DEFICIENCIA VITAMINA D AUTOTEST NEWFOUNDLAND CASETE UNIDAD | C49: si | D49: NEWFOUNDLAND | E49: 59000 | F49: =+VLOOKUP(B49,Distribuidor!$B$7:$D$533,3,0) -> 41200 | G49: =+E49-F49 -> 17800 | H49: =+G49*L49 -> 89000 | I49: 12000 | J49: =+E49*1.4 -> 82600 | K49: =+J49+I49 -> 94600 | L49: 5 | M49: =+J49*L49 -> 413000 | N49: =+E49 -> 59000 | O49: =9000+N49 -> 68000 | P49: =+O49-K49 -> -26600
A50: =+A49+1 -> 44 | B50: COMPLEJO B + ZINC + VITAMINA D VITAMIN & LINE X 100 SOFTGELS | D50: VITAMIN & LINE | E50: 56000 | F50: =+VLOOKUP(B50,Distribuidor!$B$7:$D$533,3,0) -> 39100 | G50: =+E50-F50 -> 16900 | I50: 12000 | J50: =+E50*1.4 -> 78400 | K50: =+J50+I50 -> 90400
A51: =+A50+1 -> 45 | B51: ISOFLAVONAS DE SOYA + CALCIO + VIT. D3 VITAMIN & LINE X 100 SOFTGELS | D51: VITAMIN & LINE | E51: 55000 | F51: =+VLOOKUP(B51,Distribuidor!$B$7:$D$533,3,0) -> 38500 | G51: =+E51-F51 -> 16500 | I51: 12000 | J51: =+E51*1.4 -> 77000 | K51: =+J51+I51 -> 89000
A52: =+A51+1 -> 46 | B52: LIPFAST-NAT NATURAL LIGHT X 60 CAPSULAS | D52: NATURAL LIGHT | E52: 54000 | F52: =+VLOOKUP(B52,Distribuidor!$B$7:$D$533,3,0) -> 37200 | G52: =+E52-F52 -> 16800 | I52: 12000 | J52: =+E52*1.4 -> 75600 | K52: =+J52+I52 -> 87600
A53: =+A52+1 -> 47 | B53: ALOE VERA + VITAMINA E LOCION IMPORTADO VITAMIN & LINE X 60 SOFTGELS | D53: VITAMIN & LINE | E53: 54000 | F53: =+VLOOKUP(B53,Distribuidor!$B$7:$D$533,3,0) -> 37800 | G53: =+E53-F53 -> 16200 | I53: 12000 | J53: =+E53*1.4 -> 75600 | K53: =+J53+I53 -> 87600
A54: =+A53+1 -> 48 | B54: COLAGENO HIDRO. + BIOTINA + VIT. E UVA VITAMIN & LINE JARABE X 1000 ML | D54: VITAMIN & LINE | E54: 54000 | F54: =+VLOOKUP(B54,Distribuidor!$B$7:$D$533,3,0) -> 37800 | G54: =+E54-F54 -> 16200 | I54: 12000 | J54: =+E54*1.4 -> 75600 | K54: =+J54+I54 -> 87600
A55: =+A54+1 -> 49 | B55: GUMMY VITS (VITAGOMITAS) VITAMIN & LINE | D55: VITAMIN & LINE | E55: 54000 | F55: =+VLOOKUP(B55,Distribuidor!$B$7:$D$533,3,0) -> 37800 | G55: =+E55-F55 -> 16200 | I55: 12000 | J55: =+E55*1.4 -> 75600 | K55: =+J55+I55 -> 87600
A56: =+A55+1 -> 50 | B56: VITAMINA C 1000 MG + ZINC VITAMIN & LINE X 100 CAPSULAS | D56: VITAMIN & LINE | E56: 54000 | F56: =+VLOOKUP(B56,Distribuidor!$B$7:$D$533,3,0) -> 37800 | G56: =+E56-F56 -> 16200 | I56: 12000 | J56: =+E56*1.4 -> 75600 | K56: =+J56+I56 -> 87600
A57: =+A56+1 -> 51 | B57: ENERGY UP BEBIDA ENERGIZANTE GMN TERMO X 25 SACHETS | D57: GMN | E57: 53000 | F57: =+VLOOKUP(B57,Distribuidor!$B$7:$D$533,3,0) -> 36600 | G57: =+E57-F57 -> 16400 | I57: 12000 | J57: =+E57*1.4 -> 74200 | K57: =+J57+I57 -> 86200
A58: =+A57+1 -> 52 | B58: BRONQUISAN PASTILLAS MANA DISPLAY X 20 SOBRES | D58: EL MANA | E58: 52000 | F58: =+VLOOKUP(B58,Distribuidor!$B$7:$D$533,3,0) -> 36000 | G58: =+E58-F58 -> 16000 | I58: 12000 | J58: =+E58*1.4 -> 72800 | K58: =+J58+I58 -> 84800
A59: =+A58+1 -> 53 | B59: DI-33 PASTILLAS GARGANTA MIEL MONSER DISPLAY X 100 PASTILLAS | D59: VARIOS | E59: 52000 | F59: =+VLOOKUP(B59,Distribuidor!$B$7:$D$533,3,0) -> 36100 | G59: =+E59-F59 -> 15900 | I59: 12000 | J59: =+E59*1.4 -> 72800 | K59: =+J59+I59 -> 84800
A60: =+A59+1 -> 54 | B60: CITRA-POT (CITRATO POTASIO) VAINILLA VITAMIN & LINE POLVO 400 G | D60: VITAMIN & LINE | E60: 51000 | F60: =+VLOOKUP(B60,Distribuidor!$B$7:$D$533,3,0) -> 35200 | G60: =+E60-F60 -> 15800 | I60: 12000 | J60: =+E60*1.4 -> 71400 | K60: =+J60+I60 -> 83400
A61: =+A60+1 -> 55 | B61: CITRAMAG (CITRATO MAGNESIO) VAINILLA VITAMIN & LINE POLVO 400 G | D61: VITAMIN & LINE | E61: 51000 | F61: =+VLOOKUP(B61,Distribuidor!$B$7:$D$533,3,0) -> 35200 | G61: =+E61-F61 -> 15800 | I61: 12000 | J61: =+E61*1.4 -> 71400 | K61: =+J61+I61 -> 83400
... A69: =+A68+1 -> 63 | B69: VITAMINA D3 + CITRATO DE MAGNESIO GENESIS X 90 CAPSULAS | D69: GENESIS | E69: 43000 | F69: =+VLOOKUP(B69,Distribuidor!$B$7:$D$533,3,0) -> 30000 | G69: =+E69-F69 -> 13000 | I69: 12000 | J69: =+E69*1.4 -> 60200 | K69: =+J69+I69 -> 72200
A70: =+A69+1 -> 64 | B70: FIBERLAB (FIBRA DIETARIA) NARANJA PHARBIOLAB® POLVO X 1000 G | C70: si | D70: PHARBIOLAB® | E70: 43000 | F70: =+VLOOKUP(B70,Distribuidor!$B$7:$D$533,3,0) -> 30000 | G70: =+E70-F70 -> 13000 | H70: =+G70*L70 -> 65000 | I70: 12000 | J70: =+E70*1.4 -> 60200 | K70: =+J70+I70 -> 72200 | L70: 5 | M70: =+J70*L70 -> 301000 | N70: 60900 | O70: =9000+N70 -> 69900 | P70: =+O70-K70 -> -2300
A71: =+A70+1 -> 65 | B71: GELILAB ADVANCE (COLAGENO HIDROL.) UVA PHARBIOLAB® POLVO X 1000 G | C71: si | D71: PHARBIOLAB® | E71: 43000 | F71: =+VLOOKUP(B71,Distribuidor!$B$7:$D$533,3,0) -> 30000 | G71: =+E71-F71 -> 13000 | H71: =+G71*L71 -> 65000 | I71: 12000 | J71: =+E71*1.4 -> 60200 | K71: =+J71+I71 -> 72200 | L71: 5 | M71: =+J71*L71 -> 301000 | N71: 60900 | O71: =9000+N71 -> 69900 | P71: =+O71-K71 -> -2300
A72: =+A71+1 -> 66 | B72: SURELAB CHILDREN'S (MULTIVITAMINICO) VAINILLA PHARBIOLAB® POLVO X 1000 G | D72: PHARBIOLAB® | E72: 43000 | F72: =+VLOOKUP(B72,Distribuidor!$B$7:$D$533,3,0) -> 30000 | G72: =+E72-F72 -> 13000 | I72: 12000 | J72: =+E72*1.4 -> 60200 | K72: =+J72+I72 -> 72200
A73: =+A72+1 -> 67 | B73: SURELAB MAMA (MULTIVITAMINICO) VAINILLA PHARBIOLAB® POLVO X 1000 G | D73: PHARBIOLAB® | E73: 43000 | F73: =+VLOOKUP(B73,Distribuidor!$B$7:$D$533,3,0) -> 30000 | G73: =+E73-F73 -> 13000 | I73: 12000 | J73: =+E73*1.4 -> 60200 | K73: =+J73+I73 -> 72200
A74: =+A73+1 -> 68 | B74: SURELAB ULTRA (MULTIVITAMINICO) VAINILLA PHARBIOLAB® POLVO X 1000 G | C74: si | D74: PHARBIOLAB® | E74: 43000 | F74: =+VLOOKUP(B74,Distribuidor!$B$7:$D$533,3,0) -> 30000 | G74: =+E74-F74 -> 13000 | H74: =+G74*L74 -> 65000 | I74: 12000 | J74: =+E74*1.4 -> 60200 | K74: =+J74+I74 -> 72200 | L74: 5 | M74: =+J74*L74 -> 301000 | N74: 60900 | O74: =9000+N74 -> 69900 | P74: =+O74-K74 -> -2300
A75: =+A74+1 -> 69 | B75: SOY & SURE KIDS FRESA VITALFARMA POLVO X 400 G | D75: VITALFARMA | E75: 43000 | F75: =+VLOOKUP(B75,Distribuidor!$B$7:$D$533,3,0) -> 29500 | G75: =+E75-F75 -> 13500 | I75: 12000 | J75: =+E75*1.4 -> 60200 | K75: =+J75+I75 -> 72200
A76: =+A75+1 -> 70 | B76: SOY & SURE KIDS VAINILLA VITALFARMA POLVO X 400 G | D76: VITALFARMA | E76: 43000 | F76: =+VLOOKUP(B76,Distribuidor!$B$7:$D$533,3,0) -> 29500 | G76: =+E76-F76 -> 13500 | I76: 12000 | J76: =+E76*1.4 -> 60200 | K76: =+J76+I76 -> 72200
A77: =+A76+1 -> 71 | B77: BRONQUISAN BUCOFARINGEO MANA SPRAY X 50 ML | D77: EL MANA | E77: 42000 | F77: =+VLOOKUP(B77,Distribuidor!$B$7:$D$533,3,0) -> 29000 | G77: =+E77-F77 -> 13000 | I77: 12000 | J77: =+E77*1.4 -> 58800 | K77: =+J77+I77 -> 70800
A78: =+A77+1 -> 72 | B78: FOSFORO + CITRATO DE MAGNESIO GENESIS X 90 CAPSULAS | D78: GENESIS | E78: 42000 | F78: =+VLOOKUP(B78,Distribuidor!$B$7:$D$533,3,0) -> 29400 | G78: =+E78-F78 -> 12600 | I78: 12000 | J78: =+E78*1.4 -> 58800 | K78: =+J78+I78 -> 70800
A79: =+A78+1 -> 73 | B79: SHAMPOO MOM (FUTURAS MADRES) Mª SALOME X 400 ML | D79: MARIA SALOME | E79: 42000 | F79: =+VLOOKUP(B79,Distribuidor!$B$7:$D$533,3,0) -> 29000 | G79: =+E79-F79 -> 13000 | I79: 12000 | J79: =+E79*1.4 -> 58800 | K79: =+J79+I79 -> 70800
A80: =+A79+1 -> 74 | B80: SHAMPOO PROTECCION COLOR Mª SALOME X 400 ML | D80: MARIA SALOME | E80: 42000 | F80: =+VLOOKUP(B80,Distribuidor!$B$7:$D$533,3,0) -> 29000 | G80: =+E80-F80 -> 13000 | I80: 12000 | J80: =+E80*1.4 -> 58800 | K80: =+J80+I80 -> 70800
A81: =+A80+1 -> 75 | B81: OMEGA 3 6 9 VITAMIN & LINE X 100 SOFTGELS | D81: VITAMIN & LINE | E81: 42000 | F81: =+VLOOKUP(B81,Distribuidor!$B$7:$D$533,3,0) -> 29000 | G81: =+E81-F81 -> 13000 | I81: 12000 | J81: =+E81*1.4 -> 58800 | K81: =+J81+I81 -> 70800
A82: =+A81+1 -> 76 | B82: CITRATO DE POTASIO 900 MG + VIT. B12 600 MCG GENESIS X 90 CAPSULAS | C82: si | D82: GENESIS | E82: 41000 | F82: =+VLOOKUP(B82,Distribuidor!$B$7:$D$533,3,0) -> 28500 | G82: =+E82-F82 -> 12500 | H82: =+G82*L82 -> 62500 | I82: 12000 | J82: =+E82*1.4 -> 57400 | K82: =+J82+I82 -> 69400 | L82: 5 | M82: =+J82*L82 -> 287000 | N82: 44900 | O82: =9000+N82 -> 53900 | P82: =+O82-K82 -> -15500
A83: =+A82+1 -> 77 | B83: NATURFLORA (PRO + PREBIOTICOS) NATURFAR X 60 CAPSULAS | D83: NATURFAR | E83: 41000 | F83: =+VLOOKUP(B83,Distribuidor!$B$7:$D$533,3,0) -> 28200 | G83: =+E83-F83 -> 12800 | I83: 12000 | J83: =+E83*1.4 -> 57400 | K83: =+J83+I83 -> 69400
A84: =+A83+1 -> 78 | B84: COLAGENO MARINO HIDROLIZADO CNATURAL POLVO X 700 G | D84: CNATURAL | E84: 40000 | F84: =+VLOOKUP(B84,Distribuidor!$B$7:$D$533,3,0) -> 27900 | G84: =+E84-F84 -> 12100 | I84: 12000 | J84: =+E84*1.4 -> 56000 | K84: =+J84+I84 -> 68000
A85: =+A84+1 -> 79 | B85: COLAGENO MARINO HIDROLIZADO + VIT. C GENESIS X 90 CAPSULAS | D85: GENESIS | E85: 40000 | F85: =+VLOOKUP(B85,Distribuidor!$B$7:$D$533,3,0) -> 27900 | G85: =+E85-F85 -> 12100 | I85: 12000 | J85: =+E85*1.4 -> 56000 | K85: =+J85+I85 -> 68000
A86: =+A85+1 -> 80 | B86: TRIGOSAMINE (CLORURO+COLAGENO+VITAMINA D3) IMPROFARME X 90 CAPSULAS | D86: IMPROFARME | E86: 40000 | F86: =+VLOOKUP(B86,Distribuidor!$B$7:$D$533,3,0) -> 27500 | G86: =+E86-F86 -> 12500 | I86: 12000 | J86: =+E86*1.4 -> 56000 | K86: =+J86+I86 -> 68000
A87: =+A86+1 -> 81 | B87: REDUCTION POWER PLATINIUM NATURALPOWER X 90 + 15 CAPSULAS | D87: NATURAL POWER | E87: 40000 | F87: =+VLOOKUP(B87,Distribuidor!$B$7:$D$533,3,0) -> 27900 | G87: =+E87-F87 -> 12100 | I87: 12000 | J87: =+E87*1.4 -> 56000 | K87: =+J87+I87 -> 68000
A88: =+A87+1 -> 82 | B88: COLAGENO HIDROLIZADO NATURAL LIFE POLVO X 30 SACHETS | D88: NATURAL LIFE | E88: 39000 | F88: =+VLOOKUP(B88,Distribuidor!$B$7:$D$533,3,0) -> 27300 | G88: =+E88-F88 -> 11700 | I88: 12000 | J88: =+E88*1.4 -> 54600 | K88: =+J88+I88 -> 66600
A89: =+A88+1 -> 83 | B89: GINKGO BILOBA (80 MG) IMPORTADO NATURAL LIFE X 100 SOFTGELS | D89: NATURAL LIFE | E89: 39000 | F89: =+VLOOKUP(B89,Distribuidor!$B$7:$D$533,3,0) -> 27000 | G89: =+E89-F89 -> 12000 | I89: 12000 | J89: =+E89*1.4 -> 54600 | K89: =+J89+I89 -> 66600
A90: =+A89+1 -> 84 | B90: ISOFLAVONA DE SOYA IMPORTADO NATURAL LIFE X 100 SOFTGELS | D90: NATURAL LIFE | E90: 39000 | F90: =+VLOOKUP(B90,Distribuidor!$B$7:$D$533,3,0) -> 27000 | G90: =+E90-F90 -> 12000 | I90: 12000 | J90: =+E90*1.4 -> 54600 | K90: =+J90+I90 -> 66600
A91: =+A90+1 -> 85 | B91: VITAMINA E 400 IU IMPORTADO NATURAL LIFE X 100 SOFTGELS | D91: NATURAL LIFE | E91: 39000 | F91: =+VLOOKUP(B91,Distribuidor!$B$7:$D$533,3,0) -> 27000 | G91: =+E91-F91 -> 12000 | I91: 12000 | J91: =+E91*1.4 -> 54600 | K91: =+J91+I91 -> 66600
A92: =+A91+1 -> 86 | B92: KADEIN (CASTAÑO INDIAS) NATURFAR X 60 CAPSULAS | D92: NATURFAR | E92: 39000 | F92: =+VLOOKUP(B92,Distribuidor!$B$7:$D$533,3,0) -> 26700 | G92: =+E92-F92 -> 12300 | I92: 12000 | J92: =+E92*1.4 -> 54600 | K92: =+J92+I92 -> 66600
A93: =+A92+1 -> 87 | B93: ALIFLUS BEBIDA CALIENTE LIMON SANLY POLVO X 24 SACHETS | D93: SANLY | E93: 39000 | F93: =+VLOOKUP(B93,Distribuidor!$B$7:$D$533,3,0) -> 27000 | G93: =+E93-F93 -> 12000 | I93: 12000 | J93: =+E93*1.4 -> 54600 | K93: =+J93+I93 -> 66600
A94: =+A93+1 -> 88 | B94: SOY & SURE FT VAINILLA VITALFARMA POLVO X 400 G | D94: VITALFARMA | E94: 39000 | F94: =+VLOOKUP(B94,Distribuidor!$B$7:$D$533,3,0) -> 27000 | G94: =+E94-F94 -> 12000 | I94: 12000 | J94: =+E94*1.4 -> 54600 | K94: =+J94+I94 -> 66600
... A99: =+A98+1 -> 93 | B99: PERFUME MUJER CON FEROMONAS NATURALPOWER SPRAY X 25 ML | D99: NATURAL POWER | E99: 38000 | F99: =+VLOOKUP(B99,Distribuidor!$B$7:$D$533,3,0) -> 26400 | G99: =+E99-F99 -> 11600 | I99: 12000 | J99: =+E99*1.4 -> 53200 | K99: =+J99+I99 -> 65200
A100: =+A99+1 -> 94 | B100: CITRATO DE MAGNESIO 900 MG + VIT. C 600 MG GENESIS X 90 CAPSULAS | C100: si | D100: GENESIS | E100: 37000 | F100: =+VLOOKUP(B100,Distribuidor!$B$7:$D$533,3,0) -> 25800 | G100: =+E100-F100 -> 11200 | H100: =+G100*L100 -> 56000 | I100: 12000 | J100: =+E100*1.4 -> 51800 | K100: =+J100+I100 -> 63800 | L100: 5 | M100: =+J100*L100 -> 259000 | N100: 57900 | O100: =9000+N100 -> 66900 | P100: =+O100-K100 -> 3100
A101: =+A100+1 -> 95 | B101: CITRATO DE POTASIO 750 MG + CITRATO DE MAGNESIO 750 MG GENESIS X 90 CAPSULAS | C101: si | D101: GENESIS | E101: 37000 | F101: =+VLOOKUP(B101,Distribuidor!$B$7:$D$533,3,0) -> 25800 | G101: =+E101-F101 -> 11200 | H101: =+G101*L101 -> 56000 | I101: 12000 | J101: =+E101*1.4 -> 51800 | K101: =+J101+I101 -> 63800 | L101: 5 | M101: =+J101*L101 -> 259000 | N101: 83850 | O101: =9000+N101 -> 92850 | P101: =+O101-K101 -> 29050
A102: =+A101+1 -> 96 | B102: MELATONINA + PASSIFLORA GENESIS X 90 CAPSULAS | D102: GENESIS | E102: 37000 | F102: =+VLOOKUP(B102,Distribuidor!$B$7:$D$533,3,0) -> 25900 | G102: =+E102-F102 -> 11100 | I102: 12000 | J102: =+E102*1.4 -> 51800 | K102: =+J102+I102 -> 63800
A103: =+A102+1 -> 97 | B103: SAW PALMETTO 1500 MG GENESIS X 90 CAPSULAS | D103: GENESIS | E103: 37000 | F103: =+VLOOKUP(B103,Distribuidor!$B$7:$D$533,3,0) -> 25900 | G103: =+E103-F103 -> 11100 | I103: 12000 | J103: =+E103*1.4 -> 51800 | K103: =+J103+I103 -> 63800
A104: =+A103+1 -> 98 | B104: VITAMINA C 1500 MG GENESIS X 90 CAPSULAS | D104: GENESIS | E104: 37000 | F104: =+VLOOKUP(B104,Distribuidor!$B$7:$D$533,3,0) -> 25500 | G104: =+E104-F104 -> 11500 | I104: 12000 | J104: =+E104*1.4 -> 51800 | K104: =+J104+I104 -> 63800
A105: =+A104+1 -> 99 | B105: ACONDICIONADOR KERATIN 2 Mª SALOME X 400 ML | D105: MARIA SALOME | E105: 36000 | F105: =+VLOOKUP(B105,Distribuidor!$B$7:$D$533,3,0) -> 25100 | G105: =+E105-F105 -> 10900 | I105: 12000 | J105: =+E105*1.4 -> 50400 | K105: =+J105+I105 -> 62400
A106: =+A105+1 -> 100 | B106: TRIPLE OMEGA 369 IMPORTADO NATURAL LIFE X 100 SOFTGELS | D106: NATURAL LIFE | E106: 36000 | F106: =+VLOOKUP(B106,Distribuidor!$B$7:$D$533,3,0) -> 24700 | G106: =+E106-F106 -> 11300 | I106: 12000 | J106: =+E106*1.4 -> 50400 | K106: =+J106+I106 -> 62400
A107: =+A106+1 -> 101 | B107: CICALEN GEL ORAL (CALENDULA) NATURFAR JARABE X 360 ML | D107: NATURFAR | E107: 36000 | F107: =+VLOOKUP(B107,Distribuidor!$B$7:$D$533,3,0) -> 25000 | G107: =+E107-F107 -> 11000 | I107: 12000 | J107: =+E107*1.4 -> 50400 | K107: =+J107+I107 -> 62400
A108: =+A107+1 -> 102 | B108: LAXARDIG (FIBRA DIGESTIVA LAXANTE) CAR&MER DISPLAY X 20 SACHETS | D108: CAR&MER | E108: 35000 | F108: =+VLOOKUP(B108,Distribuidor!$B$7:$D$533,3,0) -> 24500 | G108: =+E108-F108 -> 10500 | I108: 12000 | J108: =+E108*1.4 -> 49000 | K108: =+J108+I108 -> 61000
A109: =+A108+1 -> 103 | B109: BRUSMAX (CAFE DE BRUSCA) CNATURAL POLVO X 350 G | D109: CNATURAL | E109: 35000 | F109: =+VLOOKUP(B109,Distribuidor!$B$7:$D$533,3,0) -> 24500 | G109: =+E109-F109 -> 10500 | I109: 12000 | J109: =+E109*1.4 -> 49000 | K109: =+J109+I109 -> 61000
A110: =+A109+1 -> 104 | B110: PLATA COLOIDAL CNATURAL JARABE X 240 ML | D110: CNATURAL | E110: 35000 | F110: =+VLOOKUP(B110,Distribuidor!$B$7:$D$533,3,0) -> 24500 | G110: =+E110-F110 -> 10500 | I110: 12000 | J110: =+E110*1.4 -> 49000 | K110: =+J110+I110 -> 61000
A111: =+A110+1 -> 105 | B111: A-R ARTRI-RHEUMA MANA X 60 CAPSULAS | D111: EL MANA | E111: 35000 | F111: =+VLOOKUP(B111,Distribuidor!$B$7:$D$533,3,0) -> 24000 | G111: =+E111-F111 -> 11000 | I111: 12000 | J111: =+E111*1.4 -> 49000 | K111: =+J111+I111 -> 61000
A112: =+A111+1 -> 106 | B112: NUTRA FACTORS IMPROFARME X 60 CAPSULAS | D112: IMPROFARME | E112: 35000 | F112: =+VLOOKUP(B112,Distribuidor!$B$7:$D$533,3,0) -> 23900 | G112: =+E112-F112 -> 11100 | I112: 12000 | J112: =+E112*1.4 -> 49000 | K112: =+J112+I112 -> 61000
...

Sheet TOP VENTAS
A1: Posicion | B1: Item | C1: TOP
A2: 1 | B2: POWERS'X NATURALPOWER SOBRE X 4 TABLETAS | C2: si
A3: =1+A2 -> 2 | B3: MEGAS'X AZUL NATURALPOWER PASTILLERO X 3 | C3: si
A4: =1+A3 -> 3 | B4: BRONQUISAN ADULTOS MANA JALEA X 240 ML | C4: si
A5: =1+A4 -> 4 | B5: BRONQUISAN KIDS MANA JALEA X 240 ML | C5: si
A6: =1+A5 -> 5 | B6: COMPLEJO B + ZINC + VITAMINA D3 PHARBIOL | C6: si
A7: =1+A6 -> 6 | B7: GELILAB ADVANCE (COLAGENO HIDROL.) UVA P | C7: si
A8: =1+A7 -> 7 | B8: SURELAB ULTRA (MULTIVITAMINICO) VAINILLA | C8: si
A9: =1+A8 -> 8 | B9: CITRATO DE MAGNESIO 900 MG + VIT. C 600 | C9: si
A10: =1+A9 -> 9 | B10: RAIZAN FLOMECOL JARABE X 330 ML | C10: si
A11: =1+A10 -> 10 | B11: VINAGRE DE CIDRA - MANZANA CAR&MER X 750 | C11: si
A12: =1+A11 -> 11 | B12: BRONCOX MAXX IMPROFARME JARABE X 120 ML | C12: si
A13: =1+A12 -> 12 | B13: ESENCIAS FLORALES STRES, DEPRESION, INSO | C13: si
A14: =1+A13 -> 13 | B14: AGUA DE COCO ELECTROLITOS BIOEIWA X 500 | C14: si
... A38: =1+A37 -> 37 | B38: SAVITOSITO VITALFARMA JARABE X 120 ML | C38: si
A39: =1+A38 -> 38 | B39: VINAGRE DE MANZANA CON LA MADRE GALLO X | C39: si | D39: no sale
A40: =1+A39 -> 39 | B40: CLORURO DE MAGNESIO IMPROFARME X 90 CAPS | C40: si
A41: 40 | B41: VINAGRE DE MANZANA - MIEL LA ESPERANZA X500 | C41: si | D41: no sale

Sheet Distribuidor
C2: DESTINO | D2: VERIFICAR
C3: LISTA DE PRECIOS | D3: 005
C4: DESCUENTO % | D4: 0
C5: FLETE APROXIMADO | D5: 0 - 20.000
B6: Producto / Presentacion | C6: Laboratorio | D6: TIENDA N.
B7: ACEITE DE AGUACATE ADRIANGEL X 120 ML | C7: ADRIANGEL | D7: 10000
B8: ACEITE DE AJONJOLI ADRIANGEL X 120 ML | C8: ADRIANGEL | D8: 10000
B9: ACEITE DE ALMENDRAS ADRIANGEL X 120 ML | C9: ADRIANGEL | D9: 10000
B10: ACEITE DE ARGAN SPRAY ADRIANGEL X 50 ML | C10: ADRIANGEL | D10: 21900
B11: ACEITE DE CAFE VERDE ADRIANGEL X 120 ML | C11: ADRIANGEL | D11: 10000
B12: ACEITE DE CALENDULA ADRIANGEL X 120 ML | C12: ADRIANGEL | D12: 10000
B13: ACEITE DE CANELA ADRIANGEL X 120 ML | C13: ADRIANGEL | D13: 10000
B14: ACEITE DE COCO ADRIANGEL X 120 ML | C14: ADRIANGEL | D14: 10000
B15: ACEITE DE EUCALIPTO ADRIANGEL X 120 ML | C15: ADRIANGEL | D15: 10000
B16: ACEITE DE GERMEN DE TRIGO ADRIANGEL X 120 ML | C16: ADRIANGEL | D16: 10000
B17: ACEITE DE GIRASOL ADRIANGEL X 120 ML | C17: ADRIANGEL | D17: 10200
B18: ACEITE DE JOJOBA ADRIANGEL X 120 ML | C18: ADRIANGEL | D18: 10000
... B412: ULCERA ESTOMACAL H. PYLORI AUTOTEST NEWFOUNDLAND CASETE UNIDAD | C412: NEWFOUNDLAND | D412: 50500
B413: VIH AUTOTEST NEWFOUNDLAND MIDSTREAM UNIDAD | C413: NEWFOUNDLAND
B414: CREMA POWER SENSATION COLAGENO NISSI DISPLAY X 12 SACHETS | C414: NISSI | D414: 11500
B415: CREMA POWER SENSATION COLAGENO NISSI X 750 ML | C415: NISSI | D415: 12900
B416: PROTECTOR SOLAR SUNWAY PLUS 50FPS NISSI DISPLAY X 12 SACHETS | C416: NISSI | D416: 20000
B417: PROTECTOR SOLAR SUNWAY PLUS 50FPS NISSI TUBO X 120 G | C417: NISSI | D417: 20000
B418: REPELENTE PICA FIN NISSI JABON BARRA X 50 G | C418: NISSI | D418: 9300
B419: REPELENTE PICA FIN NISSI ROLL ON X 50 ML | C419: NISSI | D419: 7900
B420: REPELENTE PICA FIN NISSI SPRAY X 120 ML | C420: NISSI | D420: 11500
B421: COLAGENO + BIOTINA PHARBIOLAB® BLISTER X 30 SOFTGELS | C421: PHARBIOLAB® | D421: 18000
B422: COLAGENO + BIOTINA PHARBIOLAB® FRASCO X 60 SOFTGELS | C422: PHARBIOLAB® | D422: 32000
B423: COMPLEJO B + ZINC + VITAMINA D3 PHARBIOLAB® BLISTER X 30 SOFTGELS | C423: PHARBIOLAB® | D423: 17200
B424: FIBERLAB (FIBRA DIETARIA) NARANJA PHARBIOLAB® POLVO X 1000 G | C424: PHARBIOLAB® | D424: 30000
B425: GELILAB ADVANCE (COLAGENO HIDROL.) UVA PHARBIOLAB® POLVO X 1000 G | C425: PHARBIOLAB® | D425: 30000
... B533: VITAMINA E 1000 UI + SELENIO IMPORTADO FARNAT BLISTER X 30 SOFTGELS | C533: VARIOS | D533: 19900
B536: PRODUCTO A DESCODIFICAR
B537: PRODUCTO SIN REGISTRO

Sheet Full Inventario
C2: DESTINO | D2: NACIONAL
C3: LISTA DE PRECIOS | D3: 002
C4: DESCUENTO % | D4: 0.15
C5: FLETE APROXIMADO | D5: A definir
B6: Producto / Presentacion | C6: Laboratorio | D6: E-COMME.
B7: ACEITE DE AGUACATE ADRIANGEL X 120 ML | C7: ADRIANGEL | D7: 15000
B8: ACEITE DE AJONJOLI ADRIANGEL X 120 ML | C8: ADRIANGEL | D8: 15000
B9: ACEITE DE ALMENDRAS ADRIANGEL X 120 ML | C9: ADRIANGEL | D9: 15000
B10: ACEITE DE ARGAN SPRAY ADRIANGEL X 50 ML | C10: ADRIANGEL | D10: 32000
B11: ACEITE DE CAFE VERDE ADRIANGEL X 120 ML | C11: ADRIANGEL | D11: 15000
B12: ACEITE DE CALENDULA ADRIANGEL X 120 ML | C12: ADRIANGEL | D12: 15000
B13: ACEITE DE CANELA ADRIANGEL X 120 ML | C13: ADRIANGEL | D13: 15000
B14: ACEITE DE COCO ADRIANGEL X 120 ML | C14: ADRIANGEL | D14: 15000
B15: ACEITE DE EUCALIPTO ADRIANGEL X 120 ML | C15: ADRIANGEL | D15: 15000
B16: ACEITE DE GERMEN DE TRIGO ADRIANGEL X 120 ML | C16: ADRIANGEL | D16: 15000
B17: ACEITE DE GIRASOL ADRIANGEL X 120 ML | C17: ADRIANGEL | D17: 15000
B18: ACEITE DE JOJOBA ADRIANGEL X 120 ML | C18: ADRIANGEL | D18: 15000
... B533: VITAMINA E 1000 UI + SELENIO IMPORTADO FARNAT BLISTER X 30 SOFTGELS | C533: VARIOS | D533: 29000
B536: PRODUCTO A DESCODIFICAR
B537: PRODUCTO SIN REGISTRO
